tesseractrapidfuzz/README.MD
tesseractrapidfuzz/__init__.py
tesseractrapidfuzz/requirements.txt
tesseractrapidfuzz/thirdparty.json
tesseractrapidfuzz-0.10.dist-info/LICENSE.rst
tesseractrapidfuzz-0.10.dist-info/METADATA
tesseractrapidfuzz-0.10.dist-info/WHEEL
tesseractrapidfuzz-0.10.dist-info/top_level.txt
tesseractrapidfuzz-0.10.dist-info/RECORD
