Metadata-Version: 2.1
Name: tesseractrapidfuzz
Version: 0.10
Summary: Performs OCR on a list of images using Tesseract and performs fuzzy string matching with a given list of strings.
Home-page: https://github.com/hansalemaos/tesseractrapidfuzz
Author: Johannes Fischer
Author-email: aulasparticularesdealemaosp@gmail.com
License: MIT
Keywords: tesseract,ocr,fuzzy,rapidfuzz,fuzzywuzzy
Classifier: Development Status :: 4 - Beta
Classifier: Programming Language :: Python :: 3 :: Only
Classifier: Programming Language :: Python :: 3.10
Classifier: Topic :: Software Development :: Libraries :: Python Modules
Classifier: Topic :: Utilities
License-File: LICENSE.rst
Requires-Dist: fuzzypandaswuzzy
Requires-Dist: multitessiocr
Requires-Dist: numpy
Requires-Dist: pandas
Requires-Dist: rapidfuzz
